config/__init__.py
config/config.py
config/config_models.py
modulator/__init__.py
modulator/models.py
modulator/modulator.py
server/__init__.py
server/app.py
yams/__init__.py
yams/yams.py
yams/models/yaml_model.py
SambdaTester-0.0.12.dist-info/LICENSE.txt
SambdaTester-0.0.12.dist-info/METADATA
SambdaTester-0.0.12.dist-info/WHEEL
SambdaTester-0.0.12.dist-info/entry_points.txt
SambdaTester-0.0.12.dist-info/top_level.txt
SambdaTester-0.0.12.dist-info/RECORD
